SlideSlide/Config.py
SlideSlide/PresentationMaker.py
SlideSlide/__init__.py
SlideSlide/utils.py
SlideSlide/SlideThemes/OmnitrixGreen/CoverImage.png
SlideSlide/SlideThemes/OmnitrixGreen/SlideImage.png
SlideSlide/SlideThemes/SapphireBlue/CoverImage.png
SlideSlide/SlideThemes/SapphireBlue/SideImage.png
SlideSlide/Themes/OmnitrixGreen.json
SlideSlide/Themes/SapphireBlue.json
SlideSlide/Themes/readme.md
SlideSlide-0.0.6.dist-info/METADATA
SlideSlide-0.0.6.dist-info/WHEEL
SlideSlide-0.0.6.dist-info/top_level.txt
SlideSlide-0.0.6.dist-info/RECORD
