Metadata-Version: 2.2
Name: SlideSlide
Version: 0.0.6
Summary: Simple and Silly tool to generate presentation from json 
Home-page: https://github.com/Lakshit-Karsoliya/SlideSlide
Author: Lakshit Karsoliya
Author-email: lakshitkumar220@gmail.com
Project-URL: Source, https://github.com/Lakshit-Karsoliya/SlideSlide
Project-URL: Documentation, https://github.com/Lakshit-Karsoliya/SlideSlide
Classifier: Intended Audience :: Developers
Classifier: Programming Language :: Python :: 3.10
Classifier: Topic :: Utilities
Requires-Python: >=3.8,<3.13
Requires-Dist: behave>=1.2.5
Requires-Dist: flake8>=2.0
Requires-Dist: lxml>=3.1.0
Requires-Dist: mock>=1.0.1
Requires-Dist: Pillow>=3.3.2
Requires-Dist: pyparsing>=2.0.1
Requires-Dist: pytest>=2.5
Requires-Dist: XlsxWriter>=0.5.7
Requires-Dist: python-pptx>=1.0.2
Dynamic: author
Dynamic: author-email
Dynamic: classifier
Dynamic: description
Dynamic: description-content-type
Dynamic: home-page
Dynamic: project-url
Dynamic: requires-dist
Dynamic: requires-python
Dynamic: summary
